nada_algebra/__init__.py
nada_algebra/array.py
nada_algebra/client.py
nada_algebra/context.py
nada_algebra/funcs.py
nada_algebra/types.py
nada_algebra/utils.py
nada_algebra-0.3.4.dist-info/LICENSE
nada_algebra-0.3.4.dist-info/METADATA
nada_algebra-0.3.4.dist-info/WHEEL
nada_algebra-0.3.4.dist-info/RECORD
