Metadata-Version: 2.1
Name: nada-algebra
Version: 0.3.4
Summary: Nada-Algebra is a Python library designed for algebraic operations on NumPy-like array objects on top of Nada DSL and Nillion Network.
Author: José Cabrero-Holgueras
Author-email: jose.cabrero@nillion.com
Requires-Python: >=3.10,<4.0
Classifier: Programming Language :: Python :: 3
Classifier: Programming Language :: Python :: 3.10
Classifier: Programming Language :: Python :: 3.11
Classifier: Programming Language :: Python :: 3.12
Requires-Dist: nada-dsl (>=0.2.1,<0.3.0)
Requires-Dist: numpy (>=1.26.4,<2.0.0)
Requires-Dist: py-nillion-client (>=0.2.1,<0.3.0)
